coral_ordinal/__init__.py
coral_ordinal/activations.py
coral_ordinal/layer.py
coral_ordinal/loss.py
coral_ordinal/metrics.py
coral_ordinal/version.py
coral_ordinal-0.1.8.dist-info/LICENSE
coral_ordinal-0.1.8.dist-info/METADATA
coral_ordinal-0.1.8.dist-info/WHEEL
coral_ordinal-0.1.8.dist-info/top_level.txt
coral_ordinal-0.1.8.dist-info/RECORD
