Metadata-Version: 2.1
Name: coral-ordinal
Version: 0.1.8
Summary: Tensorflow Keras implementation of CORAL ordinal regression output layer, loss, activation, and metrics
Home-page: https://github.com/ck37/coral-ordinal
Author: Chris Kennedy, Stephen Matthews, Georg M. Goerg
Author-email: chrisken@gmail.com
License: MIT
Platform: UNKNOWN
Requires-Python: >=3.6
License-File: LICENSE
Requires-Dist: numpy
Requires-Dist: tensorflow (>=2.2)
